Single cycle RISC V processor.srcs/sources_1/new/SimpleIO.v
module SimpleIO(
    input clk, rst,
    input [7:0] switches,
    input [31:0] cpu_data,
    input write_enable,
    output reg [7:0] leds
);
    always @(posedge clk or posedge rst) begin
        if(rst)
            leds <= 0;
        else if(write_enable)
            leds <= cpu_data[7:0];
    end
endmodule

Single cycle RISC V processor.srcs/sources_1/new/PerformanceCounter.v
module PerformanceCounter(
    input clk, rst, enable,
    output reg [31:0] cycle_count,
    output reg [31:0] instr_count
);
    always @(posedge clk or posedge rst) begin
        if(rst) begin
            cycle_count <= 0;
            instr_count <= 0;
        end else begin
            cycle_count <= cycle_count + 1;
            if(enable)
                instr_count <= instr_count + 1;
        end
    end
endmodule

Single cycle RISC V processor.srcs/sources_1/new/DataMemory.v
module DataMemory(
    input clk, we, re,
    input [1:0] size,        // 00=byte, 01=half, 10=word
    input sign_ext,
    input [31:0] addr, wd,
    output reg [31:0] rd
);
    reg [7:0] mem [0:255];   // Byte-addressable memory
    wire [1:0] byte_offset;
    wire [31:0] aligned_addr;
    
    assign byte_offset = addr[1:0];
    assign aligned_addr = {addr[31:2], 2'b00};
    
    // Read logic
    always @(*) begin
        case(size)
            2'b00: begin // Byte
                if(sign_ext)
                    rd = {{24{mem[addr][7]}}, mem[addr]};
                else
                    rd = {24'b0, mem[addr]};
            end
            2'b01: begin // Halfword
                if(sign_ext)
                    rd = {{16{mem[addr+1][7]}}, mem[addr+1], mem[addr]};
                else
                    rd = {16'b0, mem[addr+1], mem[addr]};
            end
            2'b10: begin // Word
                rd = {mem[aligned_addr+3], mem[aligned_addr+2], 
                      mem[aligned_addr+1], mem[aligned_addr]};
            end
            default: rd = 0;
        endcase
    end
    
    // Write logic
    always @(posedge clk) begin
        if(we) begin
            case(size)
                2'b00: mem[addr] <= wd[7:0];              // Byte
                2'b01: begin                               // Halfword
                    mem[addr] <= wd[7:0];
                    mem[addr+1] <= wd[15:8];
                end
                2'b10: begin                               // Word
                    mem[aligned_addr] <= wd[7:0];
                    mem[aligned_addr+1] <= wd[15:8];
                    mem[aligned_addr+2] <= wd[23:16];
                    mem[aligned_addr+3] <= wd[31:24];
                end
            endcase
        end
    end
endmodule

Single cycle RISC V processor.srcs/sources_1/new/ALU.v
module ALU(
    input [31:0] a, b,
    input [3:0] alu_ctrl,
    output reg [31:0] result,
    output zero, less_than
);
    always @(*) begin
        case(alu_ctrl)
            4'b0000: result = a + b;           // ADD
            4'b0001: result = a - b;           // SUB
            4'b0010: result = a & b;           // AND
            4'b0011: result = a | b;           // OR
            4'b0100: result = a ^ b;           // XOR
            4'b0101: result = a << b[4:0];     // SLL
            4'b0110: result = a >> b[4:0];     // SRL
            4'b0111: result = $signed(a) >>> b[4:0]; // SRA
            4'b1000: result = ($signed(a) < $signed(b)) ? 1 : 0; // SLT
            4'b1001: result = (a < b) ? 1 : 0; // SLTU
            4'b1010: result = b;               // PASS B (for LUI, AUIPC)
            default: result = 0;
        endcase
    end
    
    assign zero = (result == 0);
    assign less_than = ($signed(a) < $signed(b));
endmodule

Single cycle RISC V processor.srcs/sources_1/new/ImmGen.v
module ImmGen(
    input [31:0] instr,
    output reg [31:0] imm
);

    always @(*) begin
        case(instr[6:0])
            7'b0010011, 7'b0000011, 7'b1100111: // I-type (ALU, Load, JALR)
                imm = {{20{instr[31]}}, instr[31:20]};
            7'b0100011: // S-type (Store)
                imm = {{20{instr[31]}}, instr[31:25], instr[11:7]};
            7'b1100011: // B-type (Branch)
                imm = {{19{instr[31]}}, instr[31], instr[7], instr[30:25], instr[11:8], 1'b0};
            7'b1101111: // J-type (JAL)
                imm = {{11{instr[31]}}, instr[31], instr[19:12], instr[20], instr[30:21], 1'b0};
            7'b0110111, 7'b0010111: // U-type (LUI, AUIPC)
                imm = {instr[31:12], 12'b0};
            default: imm = 0;
        endcase
    end
endmodule

Single cycle RISC V processor.srcs/sources_1/new/RegisterFile.v
module RegisterFile(
    input clk, we,
    input [4:0] ra1, ra2, wa,
    input [31:0] wd,
    output [31:0] rd1, rd2
);


    reg [31:0] regs [0:31];
    integer i;
    
    initial 
        begin
            for(i=0; i<32; i=i+1)
                regs[i] = 0;
        end
        
    assign rd1 = (ra1 == 0) ? 0 : regs[ra1];
    assign rd2 = (ra2 == 0) ? 0 : regs[ra2];
    
    always @(posedge clk) 
        begin   
            if(we && wa != 0)
                regs[wa] <= wd;
        end
        
        
endmodule

Single cycle RISC V processor.srcs/sources_1/new/ControlUnit.v
module ControlUnit(
    input [6:0] opcode,
    input [2:0] funct3,
    input [6:0] funct7,
    input [11:0] imm12,
    output reg reg_write, mem_write, mem_read,
    output reg alu_src, mem_to_reg, branch, jump, jalr,
    output reg [1:0] branch_type, mem_size,
    output reg mem_sign_ext, auipc_sel, ecall, ebreak,
    output reg [3:0] alu_ctrl
);
    always @(*) begin
        // Defaults
        reg_write = 0; mem_write = 0; mem_read = 0;
        alu_src = 0; mem_to_reg = 0; branch = 0; jump = 0; jalr = 0;
        branch_type = 2'b00; mem_size = 2'b10; mem_sign_ext = 1;
        auipc_sel = 0; ecall = 0; ebreak = 0;
        alu_ctrl = 4'b0000;
        
        case(opcode)
            7'b0110011: begin // R-type
                reg_write = 1;
                alu_src = 0;
                case(funct3)
                    3'b000: alu_ctrl = (funct7[5]) ? 4'b0001 : 4'b0000; // SUB : ADD
                    3'b111: alu_ctrl = 4'b0010; // AND
                    3'b110: alu_ctrl = 4'b0011; // OR
                    3'b100: alu_ctrl = 4'b0100; // XOR
                    3'b010: alu_ctrl = 4'b1000; // SLT
                    3'b011: alu_ctrl = 4'b1001; // SLTU
                    3'b001: alu_ctrl = 4'b0101; // SLL
                    3'b101: alu_ctrl = (funct7[5]) ? 4'b0111 : 4'b0110; // SRA : SRL
                endcase
            end
            
            7'b0010011: begin // I-type ALU
                reg_write = 1;
                alu_src = 1;
                case(funct3)
                    3'b000: alu_ctrl = 4'b0000; // ADDI
                    3'b100: alu_ctrl = 4'b0100; // XORI
                    3'b110: alu_ctrl = 4'b0011; // ORI
                    3'b111: alu_ctrl = 4'b0010; // ANDI
                    3'b010: alu_ctrl = 4'b1000; // SLTI
                    3'b011: alu_ctrl = 4'b1001; // SLTIU
                    3'b001: alu_ctrl = 4'b0101; // SLLI
                    3'b101: alu_ctrl = (funct7[5]) ? 4'b0111 : 4'b0110; // SRAI : SRLI
                endcase
            end
            
            7'b0000011: begin // Load
                reg_write = 1;
                mem_read = 1;
                alu_src = 1;
                mem_to_reg = 1;
                alu_ctrl = 4'b0000;
                case(funct3)
                    3'b000: begin mem_size = 2'b00; mem_sign_ext = 1; end // LB
                    3'b001: begin mem_size = 2'b01; mem_sign_ext = 1; end // LH
                    3'b010: begin mem_size = 2'b10; mem_sign_ext = 1; end // LW
                    3'b100: begin mem_size = 2'b00; mem_sign_ext = 0; end // LBU
                    3'b101: begin mem_size = 2'b01; mem_sign_ext = 0; end // LHU
                endcase
            end
            
            7'b0100011: begin // Store
                mem_write = 1;
                alu_src = 1;
                alu_ctrl = 4'b0000;
                case(funct3)
                    3'b000: mem_size = 2'b00; // SB
                    3'b001: mem_size = 2'b01; // SH
                    3'b010: mem_size = 2'b10; // SW
                endcase
            end
            
            7'b1100011: begin // Branch
                branch = 1;
                alu_ctrl = 4'b0001; // SUB
                case(funct3)
                    3'b000: branch_type = 2'b00; // BEQ
                    3'b001: branch_type = 2'b01; // BNE
                    3'b100: branch_type = 2'b10; // BLT
                    3'b101: branch_type = 2'b11; // BGE
                    3'b110: branch_type = 2'b10; // BLTU (reuse BLT logic with unsigned)
                    3'b111: branch_type = 2'b11; // BGEU
                endcase
            end
            
            7'b1101111: begin // JAL
                reg_write = 1;
                jump = 1;
            end
            
            7'b1100111: begin // JALR
                reg_write = 1;
                jalr = 1;
                alu_src = 1;
                alu_ctrl = 4'b0000; // ADD rs1 + imm
            end
            
            7'b0110111: begin // LUI
                reg_write = 1;
                alu_src = 1;
                alu_ctrl = 4'b1010; // PASS immediate
            end
            
            7'b0010111: begin // AUIPC
                reg_write = 1;
                alu_src = 1;
                auipc_sel = 1;
                alu_ctrl = 4'b0000; // ADD PC + imm
            end
            
            7'b1110011: begin // SYSTEM
                if(funct3 == 3'b000) begin
                    if(imm12 == 12'h000) ecall = 1;
                    else if(imm12 == 12'h001) ebreak = 1;
                end
            end
        endcase
    end
endmodule

Single cycle RISC V processor.srcs/sources_1/new/InstructionMemory.v
module InstructionMemory(
    input [31:0] addr,
    output [31:0] instruction
);

    reg  [31:0] mem [0:127];
    
    initial begin
        
        // Comprehensive test program with ALL RV32I instructions
        
        // Basic arithmetic & logical
        mem[0]  = 32'h00500093; // addi x1, x0, 5     (x1 = 5)
        mem[1]  = 32'h00300113; // addi x2, x0, 3     (x2 = 3)
        mem[2]  = 32'h002081B3; // add  x3, x1, x2    (x3 = 8)
        mem[3]  = 32'h40208233; // sub  x4, x1, x2    (x4 = 2)
        mem[4]  = 32'h0020A2B3; // slt  x5, x1, x2    (x5 = 0)
        mem[5]  = 32'h0020F333; // and  x6, x1, x2    (x6 = 1)
        mem[6]  = 32'h0020E3B3; // or   x7, x1, x2    (x7 = 7)
        mem[7]  = 32'h0020C433; // xor  x8, x1, x2    (x8 = 6)
        
        // Shifts
        mem[8]  = 32'h00209493; // slli x9, x1, 2     (x9 = 20)
        mem[9]  = 32'h0010D513; // srli x10, x1, 1    (x10 = 2)
        mem[10] = 32'hFFF00593; // addi x11, x0, -1   (x11 = -1)
        mem[11] = 32'h4015D613; // srai x12, x11, 1   (x12 = -1, arith shift)
        
        // Upper immediate instructions
        mem[12] = 32'h123456B7; // lui  x13, 0x12345  (x13 = 0x12345000)
        mem[13] = 32'h00000717; // auipc x14, 0       (x14 = PC = 52)
        
        // Memory operations - Word
        mem[14] = 32'h00412223; // sw   x4, 4(x2)     (mem[7] = 2)
        mem[15] = 32'h00412783; // lw   x15, 4(x2)    (x15 = 2)
        
        // Memory operations - Byte
        mem[16] = 32'h00410823; // sb   x4, 16(x2)    (mem[19] byte = 2)
        mem[17] = 32'h01010803; // lb   x16, 16(x2)   (x16 = 2, sign-ext)
        mem[18] = 32'h01014883; // lbu  x17, 16(x2)   (x17 = 2, zero-ext)
        
        // Memory operations - Halfword  
        mem[19] = 32'hFFE00913; // addi x18, x0, -2   (x18 = -2)
        mem[20] = 32'h01211923; // sh   x18, 18(x2)   (mem[21] half = -2)
        mem[21] = 32'h01211983; // lh   x19, 18(x2)   (x19 = -2, sign-ext)
        mem[22] = 32'h01215A03; // lhu  x20, 18(x2)   (x20 = 0xFFFE, zero-ext)
        
        // Branch instructions
        mem[23] = 32'h00208863; // beq  x1, x2, 16    (not taken)
        mem[24] = 32'h00209463; // bne  x1, x2, 8     (taken, skip next)
        mem[25] = 32'h00000013; // nop (skipped)
        mem[26] = 32'h00114A63; // blt  x2, x1, 20    (taken, 3 < 5)
        mem[27] = 32'h00000013; // nop (skipped)
        mem[28] = 32'h00000013; // nop (skipped)
        mem[29] = 32'h00000013; // nop (skipped)
        mem[30] = 32'h00115463; // bge  x2, x1, 8     (not taken)
        mem[31] = 32'h00A00A93; // addi x21, x0, 10   (x21 = 10)
        
        // Jump instructions
        mem[32] = 32'h008000EF; // jal  x1, 8         (x1 = PC+4=132, jump to 136)
        mem[33] = 32'h00000013; // nop (skipped)
        mem[34] = 32'h00C00B13; // addi x22, x0, 12   (x22 = 12, at PC=136)
        mem[35] = 32'h00008067; // jalr x0, x1, 0     (jump to x1=132, return)
        mem[36] = 32'h00D00B93; // addi x23, x0, 13   (x23 = 13, back at 140)
        
        // System calls
        mem[37] = 32'h00000073; // ecall              (environment call)
        mem[38] = 32'h00100073; // ebreak             (breakpoint)
        
        // End program
        mem[39] = 32'h00000013; // nop
        mem[40] = 32'h00000013; // nop
        
     end
     
   assign instruction = mem[addr[31:2]];


endmodule

Single cycle RISC V processor.srcs/sources_1/new/PC.v
module PC(
    input clk, rst, step_mode, step_trigger, halt,
    input [31:0] pc_next,
    output reg [31:0] pc
);

    reg step_prev;
    wire step_pulse;
    
    assign step_pulse = step_trigger && !step_prev;
    
    always @(posedge clk or posedge rst)
        begin
            if(rst) 
            begin
                pc <= 0;
                step_prev <= 0;
            end 
            else 
            begin
                step_prev <= step_trigger;
                if(!halt && (!step_mode || step_pulse))
                    pc <= pc_next;
            end
        end
endmodule

Single cycle RISC V processor.srcs/sources_1/new/CPU.v
module CPU(
    input clk, rst,
    input [7:0] switches,
    input step_mode,
    input step_trigger,
    output [7:0] leds,
    output [31:0] cycle_count,
    output [31:0] instr_count,
    output [31:0] current_pc,
    output halt_flag
);
    // Wires
    wire [31:0] pc, pc_next, pc_plus4, pc_branch, pc_jump;
    wire [31:0] instr;
    wire [31:0] rd1, rd2, imm, alu_a, alu_b, alu_result, mem_data, write_data;
    wire [3:0] alu_ctrl;
    wire [1:0] branch_type, mem_size;
    wire reg_write, mem_write, mem_read, alu_src, mem_to_reg;
    wire branch, jump, jalr, mem_sign_ext, auipc_sel;
    wire ecall, ebreak, halt;
    wire zero, less_than, branch_taken;
    
    // Halt on ECALL/EBREAK
    assign halt = ecall | ebreak;
    assign halt_flag = halt;
    
    // Branch logic
    reg branch_condition;
    always @(*) begin
        case(branch_type)
            2'b00: branch_condition = zero;         // BEQ
            2'b01: branch_condition = ~zero;        // BNE
            2'b10: branch_condition = less_than;    // BLT/BLTU
            2'b11: branch_condition = ~less_than;   // BGE/BGEU
        endcase
    end
    
    assign branch_taken = branch & branch_condition;
    
    // PC logic
    assign pc_plus4 = pc + 4;
    assign pc_branch = pc + imm;
    assign pc_jump = jalr ? (alu_result & 32'hFFFFFFFE) : (pc + imm);
    assign pc_next = (jump | jalr) ? pc_jump : (branch_taken ? pc_branch : pc_plus4);
    assign current_pc = pc;
    
    // Instantiate modules
    PC pc_reg(
        .clk(clk), .rst(rst), 
        .step_mode(step_mode), .step_trigger(step_trigger),
        .halt(halt),
        .pc_next(pc_next), .pc(pc)
    );
    
    InstructionMemory imem(.addr(pc), .instruction(instr));
    
    ControlUnit ctrl(
        .opcode(instr[6:0]), .funct3(instr[14:12]), .funct7(instr[31:25]),
        .imm12(instr[31:20]),
        .reg_write(reg_write), .mem_write(mem_write), .mem_read(mem_read),
        .alu_src(alu_src), .mem_to_reg(mem_to_reg), 
        .branch(branch), .jump(jump), .jalr(jalr),
        .branch_type(branch_type), .mem_size(mem_size),
        .mem_sign_ext(mem_sign_ext), .auipc_sel(auipc_sel),
        .ecall(ecall), .ebreak(ebreak),
        .alu_ctrl(alu_ctrl)
    );
    
    RegisterFile regfile(
        .clk(clk), .we(reg_write),
        .ra1(instr[19:15]), .ra2(instr[24:20]), .wa(instr[11:7]),
        .wd(write_data), .rd1(rd1), .rd2(rd2)
    );
    
    ImmGen immgen(.instr(instr), .imm(imm));
    
    // ALU input selection
    assign alu_a = auipc_sel ? pc : rd1;
    assign alu_b = alu_src ? imm : rd2;
    
    ALU alu(
        .a(alu_a), .b(alu_b), .alu_ctrl(alu_ctrl), 
        .result(alu_result), .zero(zero), .less_than(less_than)
    );
    
    DataMemory dmem(
        .clk(clk), .we(mem_write), .re(mem_read),
        .size(mem_size), .sign_ext(mem_sign_ext),
        .addr(alu_result), .wd(rd2), .rd(mem_data)
    );
    
    // Writeback logic
    assign write_data = (jump | jalr) ? pc_plus4 : (mem_to_reg ? mem_data : alu_result);
    
    // Performance Counter
    PerformanceCounter perf_counter(
        .clk(clk), .rst(rst), 
        .enable(!halt && (!step_mode || step_trigger)),
        .cycle_count(cycle_count), 
        .instr_count(instr_count)
    );
    
    // Simple I/O
    SimpleIO io_module(
        .clk(clk), .rst(rst),
        .switches(switches),
        .cpu_data(rd1),
        .write_enable(mem_write && (alu_result == 32'hFFFF0000)),
        .leds(leds)
    );
    
    // Monitor
    always @(posedge clk) begin
        if(!rst && (!step_mode || step_trigger) && !halt) begin
            if(ecall) $display(">>> ECALL at PC=%0d", pc);
            if(ebreak) $display(">>> EBREAK at PC=%0d", pc);
        end
    end
endmodule

Single cycle RISC V processor.srcs/sim_1/new/tb.v
module tb;
    reg clk, rst;
    reg [7:0] switches;
    reg step_mode, step_trigger;
    wire [7:0] leds;
    wire [31:0] cycle_count, instr_count, current_pc;
    wire halt_flag;
    
    CPU cpu(
        .clk(clk), .rst(rst),
        .switches(switches),
        .step_mode(step_mode),
        .step_trigger(step_trigger),
        .leds(leds),
        .cycle_count(cycle_count),
        .instr_count(instr_count),
        .current_pc(current_pc),
        .halt_flag(halt_flag)
    );
    
    initial begin
        clk = 0;
        forever #5 clk = ~clk;
    end
    
    initial begin
        $dumpfile("dump.vcd");
        $dumpvars(0, tb);
        
        $display("\n========== Complete RV32I CPU Test ==========\n");
        
        rst = 1; step_mode = 0; step_trigger = 0; switches = 8'b10101010;
        #10 rst = 0;
        
        #500;
        
        $display("\n========== Performance Summary ==========");
        $display("Total Cycles:       %0d", cycle_count);
        $display("Instructions Exec:  %0d", instr_count);
        $display("CPI:                %.2f", $itor(cycle_count)/$itor(instr_count));
        $display("Halted:             %s", halt_flag ? "YES" : "NO");
        
        $display("\n========== Register Dump ==========");
        $display("x1  = %0d (x1 = JAL return)", cpu.regfile.regs[1]);
        $display("x3  = %0d (ADD)", cpu.regfile.regs[3]);
        $display("x4  = %0d (SUB)", cpu.regfile.regs[4]);
        $display("x5  = %0d (SLT)", cpu.regfile.regs[5]);
        $display("x8  = %0d (XOR)", cpu.regfile.regs[8]);
        $display("x9  = %0d (SLLI)", cpu.regfile.regs[9]);
        $display("x12 = %0d (SRAI)", cpu.regfile.regs[12]);
        $display("x13 = 0x%h (LUI)", cpu.regfile.regs[13]);
        $display("x14 = %0d (AUIPC)", cpu.regfile.regs[14]);
        $display("x15 = %0d (LW)", cpu.regfile.regs[15]);
        $display("x16 = %0d (LB)", cpu.regfile.regs[16]);
        $display("x17 = %0d (LBU)", cpu.regfile.regs[17]);
        $display("x19 = %0d (LH)", cpu.regfile.regs[19]);
        $display("x20 = 0x%h (LHU)", cpu.regfile.regs[20]);
        $display("x21 = %0d (after BLT)", cpu.regfile.regs[21]);
        $display("x22 = %0d (after JAL)", cpu.regfile.regs[22]);
        $display("x23 = %0d (after JALR)", cpu.regfile.regs[23]);
        
        $finish;
    end
endmodule

Single cycle RISC V processor.sim/sim_1/behav/xsim/dump.vcd
$date
   Mon Jan 26 09:25:44 2026
$end

$version
  2024.2.0
  $dumpfile ("dump.vcd") 
$end

$timescale
  1ps
$end

$scope module tb $end
$var reg 1 ! clk $end
$var reg 1 " rst $end
$var reg 8 # switches [7:0] $end
$var reg 1 $ step_mode $end
$var reg 1 % step_trigger $end
$var wire 8 & leds [7:0] $end
$var wire 32 ' cycle_count [31:0] $end
$var wire 32 ( instr_count [31:0] $end
$var wire 32 ) current_pc [31:0] $end
$var wire 1 * halt_flag $end
$scope module cpu $end
$var wire 1 + clk $end
$var wire 1 , rst $end
$var wire 8 - switches [7:0] $end
$var wire 1 . step_mode $end
$var wire 1 / step_trigger $end
$var wire 8 & leds [7:0] $end
$var wire 32 ' cycle_count [31:0] $end
$var wire 32 ( instr_count [31:0] $end
$var wire 32 ) current_pc [31:0] $end
$var wire 1 * halt_flag $end
$var wire 32 0 pc [31:0] $end
$var wire 32 1 pc_next [31:0] $end
$var wire 32 2 pc_plus4 [31:0] $end
$var wire 32 3 pc_branch [31:0] $end
$var wire 32 4 pc_jump [31:0] $end
$var wire 32 5 instr [31:0] $end
$var wire 32 6 rd1 [31:0] $end
$var wire 32 7 rd2 [31:0] $end
$var wire 32 8 imm [31:0] $end
$var wire 32 9 alu_a [31:0] $end
$var wire 32 : alu_b [31:0] $end
$var wire 32 ; alu_result [31:0] $end
$var wire 32 < mem_data [31:0] $end
$var wire 32 = write_data [31:0] $end
$var wire 4 > alu_ctrl [3:0] $end
$var wire 2 ? branch_type [1:0] $end
$var wire 2 @ mem_size [1:0] $end
$var wire 1 A reg_write $end
$var wire 1 B mem_write $end
$var wire 1 C mem_read $end
$var wire 1 D alu_src $end
$var wire 1 E mem_to_reg $end
$var wire 1 F branch $end
$var wire 1 G jump $end
$var wire 1 H jalr $end
$var wire 1 I mem_sign_ext $end
$var wire 1 J auipc_sel $end
$var wire 1 K ecall $end
$var wire 1 L ebreak $end
$var wire 1 M halt $end
$var wire 1 N zero $end
$var wire 1 O less_than $end
$var wire 1 P branch_taken $end
$var reg 1 Q branch_condition $end
$scope module pc_reg $end
$var wire 1 + clk $end
$var wire 1 , rst $end
$var wire 1 . step_mode $end
$var wire 1 / step_trigger $end
$var wire 1 M halt $end
$var wire 32 1 pc_next [31:0] $end
$var reg 32 R pc [31:0] $end
$var reg 1 S step_prev $end
$var wire 1 T step_pulse $end
$upscope $end
$scope module imem $end
$var wire 32 0 addr [31:0] $end
$var wire 32 5 instruction [31:0] $end
$upscope $end
$scope module ctrl $end
$var wire 7 U opcode [6:0] $end
$var wire 3 V funct3 [14:12] $end
$var wire 7 W funct7 [31:25] $end
$var wire 12 X imm12 [31:20] $end
$var reg 1 Y reg_write $end
$var reg 1 Z mem_write $end
$var reg 1 [ mem_read $end
$var reg 1 \ alu_src $end
$var reg 1 ] mem_to_reg $end
$var reg 1 ^ branch $end
$var reg 1 _ jump $end
$var reg 1 ` jalr $end
$var reg 2 a branch_type [1:0] $end
$var reg 2 b mem_size [1:0] $end
$var reg 1 c mem_sign_ext $end
$var reg 1 d auipc_sel $end
$var reg 1 e ecall $end
$var reg 1 f ebreak $end
$var reg 4 g alu_ctrl [3:0] $end
$upscope $end
$scope module regfile $end
$var wire 1 + clk $end
$var wire 1 A we $end
$var wire 5 h ra1 [19:15] $end
$var wire 5 i ra2 [24:20] $end
$var wire 5 j wa [11:7] $end
$var wire 32 = wd [31:0] $end
$var wire 32 6 rd1 [31:0] $end
$var wire 32 7 rd2 [31:0] $end
$var integer 32 k i [31:0] $end
$upscope $end
$scope module immgen $end
$var wire 32 5 instr [31:0] $end
$var reg 32 l imm [31:0] $end
$upscope $end
$scope module alu $end
$var wire 32 9 a [31:0] $end
$var wire 32 : b [31:0] $end
$var wire 4 > alu_ctrl [3:0] $end
$var reg 32 m result [31:0] $end
$var wire 1 N zero $end
$var wire 1 O less_than $end
$upscope $end
$scope module dmem $end
$var wire 1 + clk $end
$var wire 1 B we $end
$var wire 1 C re $end
$var wire 2 @ size [1:0] $end
$var wire 1 I sign_ext $end
$var wire 32 ; addr [31:0] $end
$var wire 32 7 wd [31:0] $end
$var reg 32 n rd [31:0] $end
$var wire 2 o byte_offset [1:0] $end
$var wire 32 p aligned_addr [31:0] $end
$upscope $end
$scope module perf_counter $end
$var wire 1 + clk $end
$var wire 1 , rst $end
$var wire 1 q enable $end
$var reg 32 r cycle_count [31:0] $end
$var reg 32 s instr_count [31:0] $end
$upscope $end
$scope module io_module $end
$var wire 1 + clk $end
$var wire 1 , rst $end
$var wire 8 - switches [7:0] $end
$var wire 32 6 cpu_data [31:0] $end
$var wire 1 t write_enable $end
$var reg 8 u leds [7:0] $end
$upscope $end
$upscope $end
$upscope $end
$enddefinitions $end

#0
$dumpvars
0!
1"
b10101010 #
0$
0%
b0 &
b0 '
b0 (
b0 )
0*
0+
1,
b10101010 -
0.
0/
b0 0
b100 1
b100 2
b101 3
b101 4
b10100000000000010010011 5
b0 6
b0 7
b101 8
b0 9
b101 :
b101 ;
bx <
b101 =
b0 >
b0 ?
b10 @
1A
0B
0C
1D
0E
0F
0G
0H
1I
0J
0K
0L
0M
0N
1O
0P
0Q
b0 R
0S
0T
b10011 U
b0 V
b0 W
b101 X
1Y
0Z
0[
1\
0]
0^
0_
0`
b0 a
b10 b
1c
0d
0e
0f
b0 g
b0 h
b101 i
b1 j
b100000 k
b101 l
b101 m
bx n
b1 o
b100 p
1q
b0 r
b0 s
0t
b0 u
$end

#5000
1!
1+

#10000
0!
0"
0+
0,

#15000
1!
b1 '
b1 (
b100 )
1+
b100 0
b1000 1
b1000 2
b111 3
b111 4
b1100000000000100010011 5
b11 8
b11 :
b11 ;
b11 =
b100 R
b10011 U
b0 V
b0 W
b11 X
1Y
1\
b0 h
b11 i
b10 j
b11 l
b11 m
b11 o
b0 p
b1 r
b1 s

#20000
0!
0+

#25000
1!
b10 '
b10 (
b1000 )
1+
b1000 0
b1100 1
b1100 2
b1000 3
b1000 4
b1000001000000110110011 5
b101 6
b11 7
b0 8
b101 9
b1000 ;
b1000 =
0D
0O
b1000 R
b110011 U
b0 V
b0 W
b10 X
1Y
0\
b1 h
b10 i
b11 j
b0 l
b1000 m
b0 o
b1000 p
b10 r
b10 s

#30000
0!
0+

#35000
1!
b11 '
b11 (
b1100 )
1+
b1100 0
b10000 1
b10000 2
b1100 3
b1100 4
b1000000001000001000001000110011 5
b10 ;
b10 =
b1 >
b1100 R
b110011 U
b0 V
b100000 W
b10000000010 X
1Y
b1 g
b1 h
b10 i
b100 j
b10 m
b10 o
b0 p
b11 r
b11 s

#40000
0!
0+

#45000
1!
b100 '
b100 (
b10000 )
1+
b10000 0
b10100 1
b10100 2
b10000 3
b10000 4
b1000001010001010110011 5
b0 ;
b0 =
b1000 >
1N
1Q
b10000 R
b110011 U
b10 V
b0 W
b10 X
1Y
b1000 g
b1 h
b10 i
b101 j
b0 m
b0 o
b100 r
b100 s

#50000
0!
0+

#55000
1!
b101 '
b101 (
b10100 )
1+
b10100 0
b11000 1
b11000 2
b10100 3
b10100 4
b1000001111001100110011 5
b1 ;
b1 =
b10 >
0N
0Q
b10100 R
b110011 U
b111 V
b0 W
b10 X
1Y
b10 g
b1 h
b10 i
b110 j
b1 m
b1 o
b101 r
b101 s

#60000
0!
0+

#65000
1!
b110 '
b110 (
b11000 )
1+
b11000 0
b11100 1
b11100 2
b11000 3
b11000 4
b1000001110001110110011 5
b111 ;
b111 =
b11 >
b11000 R
b110011 U
b110 V
b0 W
b10 X
1Y
b11 g
b1 h
b10 i
b111 j
b111 m
b11 o
b100 p
b110 r
b110 s

#70000
0!
0+

#75000
1!
b111 '
b111 (
b11100 )
1+
b11100 0
b100000 1
b100000 2
b11100 3
b11100 4
b1000001100010000110011 5
b110 ;
b110 =
b100 >
b11100 R
b110011 U
b100 V
b0 W
b10 X
1Y
b100 g
b1 h
b10 i
b1000 j
b110 m
b10 o
b111 r
b111 s

#80000
0!
0+

#85000
1!
b1000 '
b1000 (
b100000 )
1+
b100000 0
b100100 1
b100100 2
b100010 3
b100010 4
b1000001001010010010011 5
b10 8
b10 :
b10100 ;
b10100 =
b101 >
1D
b100000 R
b10011 U
b1 V
b0 W
b10 X
1Y
1\
b101 g
b1 h
b10 i
b1001 j
b10 l
b10100 m
b0 o
b10100 p
b1000 r
b1000 s

#90000
0!
0+

#95000
1!
b1001 '
b1001 (
b100100 )
1+
b100100 0
b101000 1
b101000 2
b100101 3
b100101 4
b100001101010100010011 5
b101 7
b1 8
b1 :
b10 ;
b10 =
b110 >
b100100 R
b10011 U
b101 V
b0 W
b1 X
1Y
1\
b110 g
b1 h
b1 i
b1010 j
b1 l
b10 m
b10 o
b0 p
b1001 r
b1001 s

#100000
0!
0+

#105000
1!
b1010 '
b1010 (
b101000 )
1+
b101000 0
b101100 1
b101100 2
b100111 3
b100111 4
b11111111111100000000010110010011 5
b0 6
b0 7
b11111111111111111111111111111111 8
b0 9
b11111111111111111111111111111111 :
b11111111111111111111111111111111 ;
b11111111111111111111111111111111 =
b0 >
0O
b101000 R
b10011 U
b0 V
b1111111 W
b111111111111 X
1Y
1\
b0 g
b0 h
b11111 i
b1011 j
b11111111111111111111111111111111 l
b11111111111111111111111111111111 m
b11 o
b11111111111111111111111111111100 p
b1010 r
b1010 s

#110000
0!
0+

#115000
1!
b1011 '
b1011 (
b101100 )
1+
b101100 0
b110000 1
b110000 2
b10000101101 3
b10000101101 4
b1000000000101011101011000010011 5
b11111111111111111111111111111111 6
b101 7
b10000000001 8
b11111111111111111111111111111111 9
b10000000001 :
b111 >
1O
b101100 R
b10011 U
b101 V
b100000 W
b10000000001 X
1Y
1\
b111 g
b1011 h
b1 i
b1100 j
b10000000001 l
b1011 r
b1011 s

#120000
0!
0+

#125000
1!
b1100 '
b1100 (
b110000 )
1+
b110000 0
b110100 1
b110100 2
b10010001101000101000000110000 3
b10010001101000101000000110000 4
b10010001101000101011010110111 5
b110 6
b1000 7
b10010001101000101000000000000 8
b110 9
b10010001101000101000000000000 :
b10010001101000101000000000000 ;
b10010001101000101000000000000 =
b1010 >
b110000 R
b110111 U
b101 V
b1001 W
b100100011 X
1Y
1\
b1010 g
b1000 h
b11 i
b1101 j
b10010001101000101000000000000 l
b10010001101000101000000000000 m
b0 o
b10010001101000101000000000000 p
b1100 r
b1100 s

#130000
0!
0+

#135000
1!
b1101 '
b1101 (
b110100 )
1+
b110100 0
b111000 1
b111000 2
b110100 3
b110100 4
b11100010111 5
b0 6
b0 7
b0 8
b110100 9
b0 :
b110100 ;
b110100 =
b0 >
1J
0O
b110100 R
b10111 U
b0 V
b0 W
b0 X
1Y
1\
1d
b0 g
b0 h
b0 i
b1110 j
b0 l
b110100 m
b110100 p
b1101 r
b1101 s

#140000
0!
0+

#145000
1!
b1110 '
b1110 (
b111000 )
1+
b111000 0
b111100 1
b111100 2
b111100 3
b111100 4
b10000010010001000100011 5
b11 6
b10 7
b100 8
b11 9
b100 :
b111 ;
b111 =
0A
1B
0J
1O
b111000 R
b100011 U
b10 V
b0 W
b100 X
0Y
1Z
1\
0d
b10 h
b100 i
b100 j
b100 l
b111 m
b11 o
b100 p
b1110 r
b1110 s

#150000
0!
0+

